easyRequestJson/__init__.py
easyRequestJson/easyRequestJson.py
easyRequestJson/easyRequestsJson.py
easyRequestJson-0.0.4.dist-info/METADATA
easyRequestJson-0.0.4.dist-info/WHEEL
easyRequestJson-0.0.4.dist-info/top_level.txt
easyRequestJson-0.0.4.dist-info/RECORD
