Metadata-Version: 2.1
Name: easyRequestJson
Version: 0.0.4
Summary: Easy do Post and Get requests
Home-page: UNKNOWN
Author: Pickled08
Author-email: alexhoward21@icloud.com
License: UNKNOWN
Platform: UNKNOWN
Requires-Dist: requests
